extrarandom/__init__.py
extrarandom/extrarandom.py
extrarandom/iterator.py
extrarandom-1.0.4.dist-info/LICENSE
extrarandom-1.0.4.dist-info/METADATA
extrarandom-1.0.4.dist-info/WHEEL
extrarandom-1.0.4.dist-info/top_level.txt
extrarandom-1.0.4.dist-info/RECORD
