Metadata-Version: 2.1
Name: extrarandom
Version: 1.0.4
Summary: More random utils
Home-page: https://github.com/tovicheung/extrarandom
Author: tovicheung
License: MIT License
Keywords: random
Classifier: License :: OSI Approved :: MIT License
Classifier: Programming Language :: Python
Classifier: Programming Language :: Python :: 3
License-File: LICENSE
